Source Code/silhaeng.py
Source Code/token_p.py
Source Code/whale.py
whale/__init__.py
whale/silhaeng.py
whale/token_p.py
whale/whale.py
whale-1.2.1.dist-info/METADATA
whale-1.2.1.dist-info/WHEEL
whale-1.2.1.dist-info/top_level.txt
whale-1.2.1.dist-info/RECORD
