Metadata-Version: 2.1
Name: whale
Version: 1.2.1
Summary: Korean programming language for elementary education
Home-page: https://github.com/ICPArne/icpa-korean-programming
Author: Jin Cheol Park
Author-email: pjc05254@gmail.com
License: UNKNOWN
Keywords: Korean
Platform: UNKNOWN
Requires-Python: >=3
